AUTHORS.md
LICENSE
MANIFEST.in
README.md
setup.py
src/pysmb_util/__init__.py
src/pysmb_util/util.py
src/pysmb_util.egg-info/PKG-INFO
src/pysmb_util.egg-info/SOURCES.txt
src/pysmb_util.egg-info/dependency_links.txt
src/pysmb_util.egg-info/not-zip-safe
src/pysmb_util.egg-info/requires.txt
src/pysmb_util.egg-info/top_level.txt
tests/test_pysmb_util.py