Metadata-Version: 2.1
Name: pysmb-util
Version: 0.1.0
Summary: Compare two tables on Vertica.
Home-page: https://github.com/andyreagan/pysmb-util
Author: Andy Reagan
Author-email: andy@andyreagan.com
License: MIT
Project-URL: Issue Tracker, https://github.com/andyreagan/pysmb-util/issues
Platform: UNKNOWN
Classifier: Development Status :: 5 - Production/Stable
Classifier: Intended Audience :: Developers
Classifier: License :: OSI Approved :: MIT License
Classifier: Operating System :: Unix
Classifier: Operating System :: POSIX
Classifier: Programming Language :: Python
Classifier: Programming Language :: Python :: 3
Classifier: Programming Language :: Python :: 3.5
Classifier: Programming Language :: Python :: 3.6
Classifier: Programming Language :: Python :: 3.7
Classifier: Programming Language :: Python :: 3.8
Classifier: Programming Language :: Python :: 3.9
Classifier: Topic :: Utilities
Requires-Python: >=3.5
